<?xml version = '1.0' encoding = 'UTF-8'?>
<Diagram class="oracle.dbtools.crest.swingui.datatypes.DPVDataTypes" id="72DFA099-1A00-45D7-8243-16ED7013108D">
<createdBy>gv250</createdBy>
<modifiedBy>gv250</modifiedBy>
<createdTime>2025-05-13 01:24:00 UTC</createdTime>
<autoRoute>false</autoRoute>
<boxInbox>true</boxInbox>
<showLegend>false</showLegend>
<showLabels>true</showLabels>
<showRelAttributes>false</showRelAttributes>
<gridEnabled>false</gridEnabled>
<showGrid>false</showGrid>
<diagramColor>-1</diagramColor>
<display>false</display>
<notation>1</notation>
<objectViews>
<OView class="oracle.dbtools.crest.swingui.datatypes.TVStructuredType" oid="47E390DE-0671-C4B1-8428-0F45CBEE18F8" otype="StructuredType" vid="699A26B3-B2E4-73A4-8F68-2CC48BC6A8FE">
<hideElementsInCurrentOnly>false</hideElementsInCurrentOnly>
<bounds x="20" y="20" width="108" height="39"/>
</OView>
<OView class="oracle.dbtools.crest.swingui.datatypes.TVStructuredType" oid="F72C39E0-D1CA-8821-2AD7-A1E95A37D3D1" otype="StructuredType" vid="85C354DA-CCDF-9E60-1E0C-A1732C6E7A19">
<hideElementsInCurrentOnly>false</hideElementsInCurrentOnly>
<bounds x="178" y="20" width="78" height="39"/>
</OView>
</objectViews>
</Diagram>